balg/__init__.py
balg/boolean.py
balg/expression.py
balg/generator.py
balg/synthesizer.py
balg-0.0.6.dist-info/METADATA
balg-0.0.6.dist-info/WHEEL
balg-0.0.6.dist-info/licenses/LICENSE
balg-0.0.6.dist-info/RECORD
