Metadata-Version: 2.3
Name: balg
Version: 0.0.6
Summary: A boolean algebra toolkit to evaluate expressions, truth tables, and produce logic diagrams
Project-URL: Homepage, https://github.com/MustafaAamir/balg
Author-email: Mustafa Aamir <mustafa.290101@gmail.com>
License: MIT License
License-File: LICENSE
Keywords: algebra,boolean,logic,logic diagram,truth table
Classifier: License :: OSI Approved :: MIT License
Classifier: Operating System :: OS Independent
Classifier: Programming Language :: Python :: 3
Requires-Python: >=3.12
Requires-Dist: graphviz
